plyddl/__init__.py
plyddl/parse.py
plyddl/parsetab.py
plyddl/pddllex.py
plyddl/pddlyacc.py
plyddl/pddl/__init__.py
plyddl/pddl/predicate.py
plyddl/pddl/domain/__init__.py
plyddl/pddl/domain/action.py
plyddl/pddl/domain/axiom.py
plyddl/pddl/domain/domain.py
plyddl/pddl/domain/requirements.py
plyddl/pddl/domain/types.py
plyddl/pddl/problem/__init__.py
plyddl/pddl/problem/goal.py
plyddl/pddl/problem/init.py
plyddl/pddl/problem/objects.py
plyddl/pddl/problem/problem.py
plyddl-0.0.3.dist-info/LICENSE
plyddl-0.0.3.dist-info/METADATA
plyddl-0.0.3.dist-info/WHEEL
plyddl-0.0.3.dist-info/top_level.txt
plyddl-0.0.3.dist-info/RECORD
